imsosorry/__init__.py
imsosorry/uwuification.py
imsosorry-1.2.1.dist-info/LICENSE
imsosorry-1.2.1.dist-info/METADATA
imsosorry-1.2.1.dist-info/WHEEL
imsosorry-1.2.1.dist-info/top_level.txt
imsosorry-1.2.1.dist-info/RECORD
