Metadata-Version: 2.1
Name: imsosorry
Version: 1.2.1
Summary: Sometimes it can be necessary to call upon the ancient arts...
Author-email: Bradley Reynolds <bradley.reynolds@darbia.dev>
License: MIT
Project-URL: repository, https://github.com/letsbuilda/imsosorry/
Project-URL: documentation, https://docs.letsbuilda.dev/imsosorry/
Requires-Python: >=3.8
License-File: LICENSE
Provides-Extra: dev
Requires-Dist: pip-tools ; extra == 'dev'
Requires-Dist: pre-commit ; extra == 'dev'
Requires-Dist: black ; extra == 'dev'
Requires-Dist: ruff ; extra == 'dev'
Provides-Extra: docs
Requires-Dist: sphinx ; extra == 'docs'
Requires-Dist: furo ; extra == 'docs'
Requires-Dist: sphinx-autoapi ; extra == 'docs'
Requires-Dist: releases ; extra == 'docs'
Provides-Extra: tests
Requires-Dist: pytest ; extra == 'tests'
